{"id":12427,"cover":{"id":118221,"alpha_channel":false,"animated":false,"game":12427,"height":1025,"image_id":"co2j7x","url":"//images.igdb.com/igdb/image/upload/t_thumb/co2j7x.jpg","width":769,"checksum":"d15a159c-b63c-25cf-6438-910d3332be7f"},"first_release_date":809827200,"genres":[{"id":5,"name":"Shooter"},{"id":31,"name":"Adventure"},{"id":33,"name":"Arcade"}],"involved_companies":[{"id":127772,"company":{"id":501,"name":"Delphine Software"},"created_at":1620181954,"developer":true,"game":12427,"porting":false,"publisher":false,"supporting":false,"updated_at":1620197732,"checksum":"49126074-3fd3-b99f-554b-0179155108b6"},{"id":127773,"company":{"id":1,"name":"Electronic Arts"},"created_at":1620181954,"developer":false,"game":12427,"porting":false,"publisher":true,"supporting":false,"updated_at":1620197732,"checksum":"ea8c0964-83dc-cf8a-f1c1-2413093cdfbd"},{"id":127774,"company":{"id":19204,"name":"JoshProd"},"created_at":1620181954,"developer":false,"game":12427,"porting":true,"publisher":true,"supporting":false,"updated_at":1620197732,"checksum":"546c6b9e-3e87-43a9-09bd-07489316b897"}],"name":"Fade to Black","screenshots":[{"id":16495,"game":12427,"height":480,"image_id":"p1p8v50xgitbty9mlokt","url":"//images.igdb.com/igdb/image/upload/t_thumb/p1p8v50xgitbty9mlokt.jpg","width":640,"checksum":"d6ebd46f-5456-4bbd-d0aa-7603231bc733"},{"id":16496,"game":12427,"height":200,"image_id":"bslx7mt1yyno0w6y8owx","url":"//images.igdb.com/igdb/image/upload/t_thumb/bslx7mt1yyno0w6y8owx.jpg","width":320,"checksum":"8995d0c7-1800-8e39-7b56-8f7222cdd38f"}],"slug":"fade-to-black","summary":"Fade to Black is an action-adventure game developed by Delphine Software International and published by Electronic Arts. It is the sequel to the 1992 video game Flashback. The game was released for DOS and PlayStation; planned Nintendo 64 and Sega Saturn versions were cancelled.","total_rating":70.5,"total_rating_count":2,"url":"https://www.igdb.com/games/fade-to-black"}