{"id":3442,"alternative_names":[{"id":68575,"name":"Lamborghini 64"}],"cover":{"id":195699,"alpha_channel":false,"animated":false,"game":3442,"height":2263,"image_id":"co4703","url":"//images.igdb.com/igdb/image/upload/t_thumb/co4703.jpg","width":1697,"checksum":"fd2fbd4c-2398-05d6-d0c8-ee575d782928"},"first_release_date":880848000,"genres":[{"id":10,"name":"Racing"}],"involved_companies":[{"id":159465,"company":{"id":1404,"name":"Titus Software"},"created_at":1640409393,"developer":false,"game":3442,"porting":false,"publisher":true,"supporting":false,"updated_at":1640425147,"checksum":"1f2ea8d8-0798-2cf4-4a96-0c7c8f3277db"},{"id":159466,"company":{"id":4830,"name":"Titus France"},"created_at":1640409393,"developer":true,"game":3442,"porting":false,"publisher":false,"supporting":false,"updated_at":1640425148,"checksum":"da5cc3cb-24dd-c59d-8ae9-1507e1fb4005"}],"name":"Automobili Lamborghini","screenshots":[{"id":109167,"game":3442,"height":1080,"image_id":"fste9sjtxhtfzzwyft1t","url":"//images.igdb.com/igdb/image/upload/t_thumb/fste9sjtxhtfzzwyft1t.jpg","width":1920,"checksum":"8c3d27f3-c54a-e8cb-7316-ebf2b7e76c52"},{"id":109168,"game":3442,"height":1080,"image_id":"vcpkmitztj0eh72tofsr","url":"//images.igdb.com/igdb/image/upload/t_thumb/vcpkmitztj0eh72tofsr.jpg","width":1920,"checksum":"6edfd36d-59f5-21a9-4725-59c03fb19410"},{"id":109169,"game":3442,"height":1080,"image_id":"rykoom0jyeb5wcxmjxvc","url":"//images.igdb.com/igdb/image/upload/t_thumb/rykoom0jyeb5wcxmjxvc.jpg","width":1920,"checksum":"27ff0f1e-d4b6-5d24-4201-8d50c5a326b0"}],"slug":"automobili-lamborghini","summary":"Automobili Lamborghini is one of the earlier racing games for the Nintendo 64, developed by Titus. 8 cars are included in this game, among them the Lamborghini Diablo, Porsche 959, Ferrari F50 and some hidden ones. The courses are quite detailed and the effects are decent, including special effects like lens flares. Races take you through six circuits in exotic areas around the world. There are 4 modes in Single Player including Arcade Mode, Championship Mode, Single Race and Time Trials. The game also includes 4 player support.","url":"https://www.igdb.com/games/automobili-lamborghini","videos":[{"id":62693,"game":3442,"name":"Gameplay Video","video_id":"cVTKyiiAeYU","checksum":"2d0ed7a6-04d4-f63f-35f5-a841eb3a6cef"}]}