{"id":6344,"alternative_names":[{"id":7216,"name":"Gekitou! Car Battler Go!!"},{"id":7217,"name":"激闘！カーバトラーGO!!"}],"cover":{"id":234096,"alpha_channel":false,"animated":false,"game":6344,"height":603,"image_id":"co50mo","url":"//images.igdb.com/igdb/image/upload/t_thumb/co50mo.jpg","width":452,"checksum":"cfa811e6-3bd0-d72f-9089-08b456bae7e4"},"first_release_date":1007078400,"genres":[{"id":10,"name":"Racing"},{"id":12,"name":"Role-playing (RPG)"}],"involved_companies":[{"id":15119,"company":{"id":1767,"name":"Victor Interactive Software"},"created_at":1398038400,"developer":false,"game":6344,"porting":false,"publisher":true,"supporting":false,"updated_at":1398124800,"checksum":"182aa9da-1ef3-1094-e932-ea240039af38"},{"id":15121,"company":{"id":1568,"name":"Ancient"},"created_at":1398038400,"developer":true,"game":6344,"porting":false,"publisher":false,"supporting":false,"updated_at":1398124800,"checksum":"c09b3683-30fd-7abb-de8f-ad1e0d9f24be"},{"id":38505,"company":{"id":716,"name":"Natsume"},"created_at":1471132800,"developer":true,"game":6344,"porting":false,"publisher":true,"supporting":false,"updated_at":1471132800,"checksum":"6140273b-aae3-464a-40e9-ac62bd2def55"}],"name":"Car Battler Joe","screenshots":[{"id":154267,"game":6344,"height":160,"image_id":"nsf6u8ljsm2ojximwg5d","url":"//images.igdb.com/igdb/image/upload/t_thumb/nsf6u8ljsm2ojximwg5d.jpg","width":240,"checksum":"6ebbb0fc-6d83-ee39-d260-c0aa463133fd"},{"id":154268,"game":6344,"height":160,"image_id":"pw3a5tcqu5lmtkdguipv","url":"//images.igdb.com/igdb/image/upload/t_thumb/pw3a5tcqu5lmtkdguipv.jpg","width":240,"checksum":"2643d793-7414-9f14-e17c-fc16f72261ba"},{"id":154269,"game":6344,"height":160,"image_id":"vcuu2040exmocisaiowa","url":"//images.igdb.com/igdb/image/upload/t_thumb/vcuu2040exmocisaiowa.jpg","width":240,"checksum":"1eb1a786-9690-349a-1909-4500dc3742db"},{"id":154270,"game":6344,"height":160,"image_id":"cchiphrknoqmwcbuskhf","url":"//images.igdb.com/igdb/image/upload/t_thumb/cchiphrknoqmwcbuskhf.jpg","width":240,"checksum":"8690e6e8-f592-2fd1-27e4-2e4714c3cdcb"},{"id":154271,"game":6344,"height":160,"image_id":"qahc3z8r41mrgygbq3bw","url":"//images.igdb.com/igdb/image/upload/t_thumb/qahc3z8r41mrgygbq3bw.jpg","width":240,"checksum":"c2e78f82-1af0-eb68-20f7-75529a50d5cc"},{"id":154272,"game":6344,"height":160,"image_id":"iparcfdyigkiuychpfn1","url":"//images.igdb.com/igdb/image/upload/t_thumb/iparcfdyigkiuychpfn1.jpg","width":240,"checksum":"2a6457da-a042-c145-0fbf-d4bcb2e38361"},{"id":154273,"game":6344,"height":160,"image_id":"ziwiqtjnka6aw5ng0b4f","url":"//images.igdb.com/igdb/image/upload/t_thumb/ziwiqtjnka6aw5ng0b4f.jpg","width":240,"checksum":"0e94d0d2-f43f-5bd4-3c8b-cb7e34b4e1a9"},{"id":154274,"game":6344,"height":160,"image_id":"cax8o4rsy1ryoyv8pv07","url":"//images.igdb.com/igdb/image/upload/t_thumb/cax8o4rsy1ryoyv8pv07.jpg","width":240,"checksum":"55990759-97cd-9906-7b31-882e9acae9ed"}],"slug":"car-battler-joe","storyline":"\"The road to becoming a car battler is not an easy one.\nNobody knows why your dad, champion car battler Jim Todoroki, suddenly abandoned the fastest and most popular sport in Galacia. There is a rumor going around that he's riding around with the most ruthless car-battler gangs in the world. But is it just a rumor, or is there truth behind it?\"","summary":"Play as Joe Todoroki in his quest to become a car battler - like his father before him. His mother says he has the talent, but hard work will be the payoff. Customize a vehicle in the Garage to enhance or diminish its performance. Sign up for jobs, missions, and even tournaments as Joe explores the dangerous highways and byways that surround his village. Other car battlers fight for money and fame, but Joe has a higher calling: to restore his family's honor and bring his father home in Car Battler Joe, a racing RPG!","url":"https://www.igdb.com/games/car-battler-joe"}