{"id":4800,"cover":{"id":4750,"game":4800,"height":357,"image_id":"jt9qw9wkcbsgktev0ix9","url":"//images.igdb.com/igdb/image/upload/t_thumb/jt9qw9wkcbsgktev0ix9.jpg","width":252,"checksum":"301d74ec-0b84-04de-5d53-07a30664d2c8"},"first_release_date":1162771200,"franchise":{"id":292,"name":"Deal or No Deal"},"genres":[{"id":15,"name":"Strategy"},{"id":26,"name":"Quiz/Trivia"}],"involved_companies":[{"id":11556,"company":{"id":2102,"name":"Zoo Games"},"created_at":1391299200,"developer":false,"game":4800,"porting":false,"publisher":true,"supporting":false,"updated_at":1391299200,"checksum":"c131022f-c8d0-cf01-8b2c-64a34ce1437c"},{"id":11557,"company":{"id":354,"name":"DSI Games"},"created_at":1391299200,"developer":false,"game":4800,"porting":false,"publisher":true,"supporting":false,"updated_at":1391299200,"checksum":"a33f0df6-5893-b346-a1cd-19ac87ef830d"},{"id":11558,"company":{"id":489,"name":"Mindscape"},"created_at":1391299200,"developer":false,"game":4800,"porting":false,"publisher":true,"supporting":false,"updated_at":1391299200,"checksum":"bc87ea7d-792b-906c-0767-8458d085f918"},{"id":11559,"company":{"id":268,"name":"Global Star Software"},"created_at":1391299200,"developer":false,"game":4800,"porting":false,"publisher":true,"supporting":false,"updated_at":1391299200,"checksum":"8e065e9f-4e4c-029c-ef20-f1962cae589b"},{"id":11560,"company":{"id":2156,"name":"Imagination Entertainment"},"created_at":1391299200,"developer":true,"game":4800,"porting":false,"publisher":true,"supporting":false,"updated_at":1391299200,"checksum":"6620ead4-98b5-b5a4-aa1c-20fa68a018ca"},{"id":11561,"company":{"id":2000,"name":"Cat Daddy Games"},"created_at":1391299200,"developer":true,"game":4800,"porting":false,"publisher":false,"supporting":false,"updated_at":1391299200,"checksum":"59970d32-cf34-26c1-4e6d-40e0a8322f65"},{"id":11562,"company":{"id":2157,"name":"Gravity-i"},"created_at":1391299200,"developer":true,"game":4800,"porting":false,"publisher":false,"supporting":false,"updated_at":1391299200,"checksum":"98457154-2c1e-c5c9-a2f0-f3cd4b0ecb87"},{"id":11563,"company":{"id":1316,"name":"Black Lantern Studios"},"created_at":1391299200,"developer":true,"game":4800,"porting":false,"publisher":false,"supporting":false,"updated_at":1391299200,"checksum":"4c4ae9ff-7c1e-e0c3-fbbb-073dae276f88"}],"name":"Deal or No Deal","screenshots":[{"id":263856,"alpha_channel":false,"animated":false,"game":4800,"height":186,"image_id":"sc5nlc","url":"//images.igdb.com/igdb/image/upload/t_thumb/sc5nlc.jpg","width":271,"checksum":"343e1081-c0c5-8bca-9b6e-1d98c94430b7"},{"id":263857,"alpha_channel":false,"animated":false,"game":4800,"height":720,"image_id":"sc5nld","url":"//images.igdb.com/igdb/image/upload/t_thumb/sc5nld.jpg","width":1280,"checksum":"c5c7ae45-d847-e50e-2937-2ab8d3f0651a"},{"id":263858,"alpha_channel":false,"animated":false,"game":4800,"height":225,"image_id":"sc5nle","url":"//images.igdb.com/igdb/image/upload/t_thumb/sc5nle.jpg","width":400,"checksum":"131f18a9-da47-418e-a219-b21b735b80e6"}],"slug":"deal-or-no-deal","summary":"The hit TV show is coming to your favorite video game system! The premise is simple: You have 26 briefcases in front of you. Each one contains a different amount of money. Open each case one by one, and try to find the briefcase with the biggest amount of money. Deal Or No Deal? \n \nSingle Player \n3 single play modes tv game, puzzle game, memory \nMulitplay allows you to play as contestant or the banker \nMultiplayer on Nintendo DS","total_rating":28,"total_rating_count":2,"url":"https://www.igdb.com/games/deal-or-no-deal","videos":[{"id":23245,"game":4800,"name":"Gameplay video","video_id":"BkyCCYcoWiw","checksum":"cdf9b9a5-ec64-8cbe-157c-6c39b9cbcf22"}]}