{"id":49697,"alternative_names":[{"id":72338,"name":"メダロットnavi カブト"}],"cover":{"id":226036,"alpha_channel":false,"animated":false,"game":49697,"height":800,"image_id":"co4ues","url":"//images.igdb.com/igdb/image/upload/t_thumb/co4ues.jpg","width":600,"checksum":"cf7f3100-7c4d-d5ec-df62-6b0368cef95e"},"first_release_date":999820800,"genres":[{"id":12,"name":"Role-playing (RPG)"}],"involved_companies":[{"id":147306,"company":{"id":191,"name":"Imagineer"},"created_at":1630645257,"developer":false,"game":49697,"porting":false,"publisher":true,"supporting":false,"updated_at":1630871254,"checksum":"19df4568-f1e1-8392-e332-d2b24675d198"},{"id":147307,"company":{"id":716,"name":"Natsume"},"created_at":1630645257,"developer":true,"game":49697,"porting":false,"publisher":false,"supporting":false,"updated_at":1630871254,"checksum":"404eb74b-3a1b-4766-f2b6-5d8b9d3b7ca4"}],"name":"Medarot Navi: Kabuto Version","slug":"medarot-navi-kabuto-version","summary":"Medarot Navi: Kabuto Version is a Role-Playing game, developed by Natsume and published by Imagineer, which was released in Japan in 2001.","url":"https://www.igdb.com/games/medarot-navi-kabuto-version"}