{"id":6787,"alternative_names":[{"id":69864,"name":"ダブルドラゴン"},{"id":69865,"name":"DD"}],"cover":{"id":93864,"alpha_channel":false,"animated":false,"game":6787,"height":826,"image_id":"co20fc","url":"//images.igdb.com/igdb/image/upload/t_thumb/co20fc.jpg","width":620,"checksum":"cb040b00-e406-85f6-7a6e-e1da02851167"},"first_release_date":554774400,"genres":[{"id":4,"name":"Fighting"},{"id":8,"name":"Platform"},{"id":25,"name":"Hack and slash/Beat 'em up"},{"id":31,"name":"Adventure"},{"id":33,"name":"Arcade"}],"involved_companies":[{"id":53742,"company":{"id":1985,"name":"Melbourne House"},"created_at":1503964800,"developer":false,"game":6787,"porting":false,"publisher":true,"supporting":false,"updated_at":1503964800,"checksum":"ba2b0e2a-3b3f-d303-b400-3029a10b12dd"},{"id":53743,"company":{"id":12390,"name":"Virgin Mastertronic"},"created_at":1503964800,"developer":false,"game":6787,"porting":false,"publisher":true,"supporting":false,"updated_at":1503964800,"checksum":"4ab6ab49-c9b2-2b95-5c07-ee54b15c1b08"},{"id":53744,"company":{"id":66,"name":"Activision"},"created_at":1503964800,"developer":false,"game":6787,"porting":false,"publisher":true,"supporting":false,"updated_at":1503964800,"checksum":"105a8d05-cdb7-0f55-7abf-0104f9b8018b"},{"id":53745,"company":{"id":4822,"name":"Arcadia Systems"},"created_at":1503964800,"developer":false,"game":6787,"porting":false,"publisher":true,"supporting":false,"updated_at":1503964800,"checksum":"496e83e4-f6e8-c593-d0dd-ad89b08113ee"},{"id":53748,"company":{"id":11694,"name":"Ballistic"},"created_at":1503964800,"developer":false,"game":6787,"porting":false,"publisher":true,"supporting":false,"updated_at":1503964800,"checksum":"bb7d50c9-1993-599a-8527-137a0e0f1a36"},{"id":53749,"company":{"id":2759,"name":"Telegames"},"created_at":1503964800,"developer":false,"game":6787,"porting":false,"publisher":true,"supporting":false,"updated_at":1503964800,"checksum":"f2eb4925-9430-fafb-6777-91c9f0126fe9"},{"id":53750,"company":{"id":13365,"name":"Zemina Co."},"created_at":1503964800,"developer":false,"game":6787,"porting":false,"publisher":true,"supporting":false,"updated_at":1503964800,"checksum":"4e722ae5-9768-47ed-8944-5a77f7d7995b"},{"id":53752,"company":{"id":340,"name":"Empire Interactive"},"created_at":1503964800,"developer":false,"game":6787,"porting":false,"publisher":true,"supporting":false,"updated_at":1503964800,"checksum":"82a379c5-b3e6-8bd4-c798-cec07c0bb66c"},{"id":94574,"company":{"id":4981,"name":"Sega Enterprises"},"created_at":1584662400,"developer":false,"game":6787,"porting":false,"publisher":true,"supporting":false,"updated_at":1584662400,"checksum":"84dd6030-391b-5b3c-88e7-1ef230add739"},{"id":135149,"company":{"id":1218,"name":"Arc System Works"},"created_at":1621198945,"developer":true,"game":6787,"porting":false,"publisher":true,"supporting":false,"updated_at":1621251472,"checksum":"e8d10af3-ae86-61a6-5250-08bce179da06"},{"id":140830,"company":{"id":512,"name":"Ocean"},"created_at":1625207323,"developer":false,"game":6787,"porting":false,"publisher":true,"supporting":false,"updated_at":1625213832,"checksum":"efb5044f-d7f3-5f77-e885-a97eebde0fe6"},{"id":176970,"company":{"id":1753,"name":"Technos Japan"},"created_at":1656253592,"developer":true,"game":6787,"porting":false,"publisher":true,"supporting":false,"updated_at":1656254500,"checksum":"cb3ea08b-0807-6da9-ce53-f95bffad6a84"},{"id":176971,"company":{"id":1753,"name":"Technos Japan"},"created_at":1656253592,"developer":true,"game":6787,"porting":false,"publisher":false,"supporting":false,"updated_at":1656254500,"checksum":"d78923c1-adbe-0b64-3272-5028e3b00aa5"}],"name":"Double Dragon","screenshots":[{"id":29418,"game":6787,"height":360,"image_id":"ftfk5zx4x9v5wf4wjzdy","url":"//images.igdb.com/igdb/image/upload/t_thumb/ftfk5zx4x9v5wf4wjzdy.jpg","width":480,"checksum":"1f987522-21b3-bd1c-dec9-4f6b1c29fb6b"},{"id":292238,"alpha_channel":false,"animated":false,"game":6787,"height":224,"image_id":"sc69hq","url":"//images.igdb.com/igdb/image/upload/t_thumb/sc69hq.jpg","width":320,"checksum":"9acc8df7-55fb-e808-fef5-98a1ac840a17"},{"id":292239,"alpha_channel":false,"animated":false,"game":6787,"height":224,"image_id":"sc69hr","url":"//images.igdb.com/igdb/image/upload/t_thumb/sc69hr.jpg","width":320,"checksum":"dabd4369-ce5e-c904-56d9-3836dee62b3d"},{"id":509645,"alpha_channel":false,"animated":false,"game":6787,"height":272,"image_id":"scax8t","url":"//images.igdb.com/igdb/image/upload/t_thumb/scax8t.jpg","width":384,"checksum":"6e52dc73-5d0d-b3e2-3733-48db6e523a10"},{"id":509646,"alpha_channel":true,"animated":false,"game":6787,"height":272,"image_id":"scax8u","url":"//images.igdb.com/igdb/image/upload/t_thumb/scax8u.jpg","width":384,"checksum":"601066e5-2189-24cd-186f-01d362c642d2"},{"id":509647,"alpha_channel":true,"animated":false,"game":6787,"height":272,"image_id":"scax8v","url":"//images.igdb.com/igdb/image/upload/t_thumb/scax8v.jpg","width":384,"checksum":"f0bae5a8-2a5c-b0af-f97c-851c0f6b4796"},{"id":509648,"alpha_channel":false,"animated":false,"game":6787,"height":272,"image_id":"scax8w","url":"//images.igdb.com/igdb/image/upload/t_thumb/scax8w.jpg","width":384,"checksum":"7dd7513c-5bb0-be1b-a7de-eee84af286ce"},{"id":509649,"alpha_channel":false,"animated":false,"game":6787,"height":272,"image_id":"scax8x","url":"//images.igdb.com/igdb/image/upload/t_thumb/scax8x.jpg","width":384,"checksum":"cb44b8db-51b7-97e2-b8c0-67db41d51fa6"},{"id":509656,"alpha_channel":false,"animated":false,"game":6787,"height":272,"image_id":"scax94","url":"//images.igdb.com/igdb/image/upload/t_thumb/scax94.jpg","width":384,"checksum":"4362c606-fdf1-1865-68e2-d82cc992cc4b"},{"id":509657,"alpha_channel":false,"animated":false,"game":6787,"height":272,"image_id":"scax95","url":"//images.igdb.com/igdb/image/upload/t_thumb/scax95.jpg","width":384,"checksum":"867821df-fa4f-c7e7-22e1-e2785456133b"},{"id":509658,"alpha_channel":true,"animated":false,"game":6787,"height":272,"image_id":"scax96","url":"//images.igdb.com/igdb/image/upload/t_thumb/scax96.jpg","width":384,"checksum":"beaa5bb8-3a44-70d5-6636-15abe98eab32"}],"slug":"double-dragon","storyline":"The player takes control of martial artist Billy Lee, or his twin brother Jimmy (also known as Hammer and Spike in the supplementary materials for the American arcade release), as they fight their way into the turf of the Black Warriors gang in order to rescue their common love interest Marian.","summary":"The player character has a repertoire of martial art techniques which they can perform by using the joystick and three action buttons (kick, jump, and punch) individually or in combination. Techniques range from basic punches and kicks, to more elaborate manoeuvres like hair grabbing moves and elbow strikes. When playing with another player, one can assist the other by grabbing their partner's opponent from behind. Caution should be taken, though, as some enemies are able to do the same thing to the players. The player begins the game with a certain number of extra lives and a life gauge which depletes as the player takes hits. If the life gauge runs out or the time limit reaches zero, the player will lose a life.\n\nThere is a small variety of enemy characters that the player will face through the course of the game. Certain enemies carry melee weapons, which can be knocked out of their hands and picked up to use against them. Available weapons include baseball bats, whips, throwing knives, and dynamite; in addition, rocks, oil drums, and boxes can be found in certain places.\n\nThe game is divided into four different stages or \"missions,\" which consist of a city slum, a factory, the woods, and the gang's hideout. The game normally ends if a single player defeats the final boss alone. However, if two players manage to complete the game together, they are then forced to fight each other in order to determine who will win Marian's affections.","total_rating":56.61290038034285,"total_rating_count":135,"url":"https://www.igdb.com/games/double-dragon","videos":[{"id":2422,"game":6787,"name":"Gameplay video","video_id":"cy5f9ayBHbM","checksum":"1f432c0c-94e2-a90e-6245-12d91ba2bb74"}]}