{"id":4080,"cover":{"id":4308,"game":4080,"height":303,"image_id":"bp7zoti6ljg1d5lisgxo","url":"//images.igdb.com/igdb/image/upload/t_thumb/bp7zoti6ljg1d5lisgxo.jpg","width":215,"checksum":"21d41507-1adf-4dff-51b3-ddda6c20ecc9"},"first_release_date":1022803200,"genres":[{"id":10,"name":"Racing"},{"id":14,"name":"Sport"}],"involved_companies":[{"id":10569,"company":{"id":485,"name":"SCi Games"},"created_at":1390435200,"developer":false,"game":4080,"porting":false,"publisher":true,"supporting":false,"updated_at":1390521600,"checksum":"b76e7404-6a8d-48b9-91fc-cfda1e6990e3"},{"id":10570,"company":{"id":259,"name":"Warthog Games"},"created_at":1390435200,"developer":true,"game":4080,"porting":false,"publisher":false,"supporting":false,"updated_at":1390521600,"checksum":"ab98eec4-2054-95b7-0749-9127f36958b6"},{"id":10571,"company":{"id":2006,"name":"Encore Software Inc."},"created_at":1390435200,"developer":false,"game":4080,"porting":false,"publisher":true,"supporting":false,"updated_at":1390521600,"checksum":"493d92c3-75e6-7793-ea69-21900423fd76"}],"name":"Rally Championship","slug":"rally-championship","summary":"Mud! Sweat! Gears! \nDirt! Snow! Rain! \n \n-25 officially licensed rally racing cars. \n-33 races in 6 prestigious rallies over 4 global regions. \n-4-Player simultaneous split-screen intense action. \n-Real car physics simulate all wheel & 2-wheel drive. \n-Extreme weather conditions test your driving skills.","total_rating":50,"total_rating_count":1,"url":"https://www.igdb.com/games/rally-championship"}