{"id":48714,"cover":{"id":164146,"alpha_channel":false,"animated":false,"game":48714,"height":401,"image_id":"co3inm","url":"//images.igdb.com/igdb/image/upload/t_thumb/co3inm.jpg","width":300,"checksum":"913ed766-1991-f23c-58b5-9d19df15a3ab"},"first_release_date":1490659200,"genres":[{"id":8,"name":"Platform"}],"name":"Dreamworld Pogie","slug":"dreamworld-pogie","summary":"Travel through 15 sugarcoated levels of arcade action with everybody's loveable pet fluffle - Pogie\n\nAnother rediscovered classic game from The Oliver Twins.","url":"https://www.igdb.com/games/dreamworld-pogie"}