{"id":72710,"alternative_names":[{"id":58071,"name":"Peter Pan and the Pirates"},{"id":58072,"name":"Peter Pan & the Pirates"},{"id":58073,"name":"Fox's Peter Pan and the Pirates"},{"id":58074,"name":"Fox's Peter Pan & the Pirates"},{"id":58075,"name":"Fox's Peter Pan and the Pirates: The Revenge of Captain Cook"},{"id":58076,"name":"Peter Pan and the Pirates: The Revenge of Captain Cook"},{"id":58077,"name":"Peter Pan & the Pirates: The Revenge of Captain Cook"}],"cover":{"id":135877,"alpha_channel":false,"animated":false,"game":72710,"height":1800,"image_id":"co2wud","url":"//images.igdb.com/igdb/image/upload/t_thumb/co2wud.jpg","width":1350,"checksum":"ff355829-e4fa-16dc-4880-e4de5e71c1d8"},"first_release_date":662688000,"genres":[{"id":8,"name":"Platform"}],"involved_companies":[{"id":123185,"company":{"id":4066,"name":"Equilibrium"},"created_at":1617237592,"developer":true,"game":72710,"porting":false,"publisher":false,"supporting":false,"updated_at":1617264626,"checksum":"50cb43c9-d927-d043-07ca-3531dc0a965f"},{"id":123186,"company":{"id":197,"name":"THQ"},"created_at":1617237592,"developer":false,"game":72710,"porting":false,"publisher":true,"supporting":false,"updated_at":1617264626,"checksum":"52df053e-cba0-5f03-cf27-4eb8968ed4d5"}],"name":"Fox's Peter Pan & The Pirates: The Revenge of Captain Hook","screenshots":[{"id":429298,"alpha_channel":true,"animated":false,"game":72710,"height":240,"image_id":"sc978y","url":"//images.igdb.com/igdb/image/upload/t_thumb/sc978y.jpg","width":256,"checksum":"ae45d183-1781-59a1-62db-fad6fcfca9f8"},{"id":429299,"alpha_channel":true,"animated":false,"game":72710,"height":240,"image_id":"sc978z","url":"//images.igdb.com/igdb/image/upload/t_thumb/sc978z.jpg","width":256,"checksum":"df0f724d-4f46-4baf-0669-81b97b6d3c22"},{"id":429300,"alpha_channel":false,"animated":false,"game":72710,"height":224,"image_id":"sc9790","url":"//images.igdb.com/igdb/image/upload/t_thumb/sc9790.jpg","width":256,"checksum":"ebf19df5-f28f-3f46-9992-1f022f77ac01"}],"slug":"foxs-peter-pan-and-the-pirates-the-revenge-of-captain-hook","summary":"Play as Peter Pan as you attempt to defeat Captain Hook and his pirates in this game based on an animated TV series.","url":"https://www.igdb.com/games/foxs-peter-pan-and-the-pirates-the-revenge-of-captain-hook"}