{"id":92724,"cover":{"id":134039,"alpha_channel":false,"animated":false,"game":92724,"height":377,"image_id":"co2vfb","url":"//images.igdb.com/igdb/image/upload/t_thumb/co2vfb.jpg","width":264,"checksum":"a068f1e0-5060-98ec-7e8d-7d357b9a0ae1"},"first_release_date":662601600,"name":"Harlem Globetrotters","slug":"harlem-globetrotters","summary":"Harlem Globetrotters is a multiplatform sports video game for the Nintendo Entertainment System and MS-DOS. The game allows players to control the Harlem Globetrotters basketball team.","url":"https://www.igdb.com/games/harlem-globetrotters"}