{"id":1658,"alternative_names":[{"id":66436,"name":"MFF"},{"id":112504,"name":"マイティファイナルファイト"}],"collection":{"id":328,"created_at":1351290647,"games":[1655,1656,1657,1658,1659,1660,1663,1664,21098,42554,203293],"name":"Final Fight","slug":"final-fight","updated_at":1668427557,"url":"https://www.igdb.com/collections/final-fight","checksum":"a9dfdec2-8ed2-4cbf-be93-07f33a7c2d33"},"cover":{"id":155675,"alpha_channel":false,"animated":false,"game":1658,"height":842,"image_id":"co3c4b","url":"//images.igdb.com/igdb/image/upload/t_thumb/co3c4b.jpg","width":632,"checksum":"03a5245b-2dcb-88b5-c296-2189fb5ee92f"},"first_release_date":739756800,"genres":[{"id":4,"name":"Fighting"},{"id":25,"name":"Hack and slash/Beat 'em up"},{"id":33,"name":"Arcade"}],"involved_companies":[{"id":178145,"company":{"id":37,"name":"Capcom"},"created_at":1657219120,"developer":true,"game":1658,"porting":false,"publisher":true,"supporting":false,"updated_at":1657297847,"checksum":"303225dd-28ab-266c-245a-71b45b13e73d"}],"name":"Mighty Final Fight","screenshots":[{"id":165700,"game":1658,"height":240,"image_id":"rz6g9t4z47dafhpdxgvm","url":"//images.igdb.com/igdb/image/upload/t_thumb/rz6g9t4z47dafhpdxgvm.jpg","width":400,"checksum":"c8fe6acc-bcc8-6f8b-f038-be8e2c31fbc8"},{"id":165701,"game":1658,"height":240,"image_id":"phwsfwawm3f2vpshxnz5","url":"//images.igdb.com/igdb/image/upload/t_thumb/phwsfwawm3f2vpshxnz5.jpg","width":400,"checksum":"292267d2-1764-6e80-d30f-850ff2f554e3"},{"id":165702,"game":1658,"height":240,"image_id":"pgnpm55mntgebyiov0re","url":"//images.igdb.com/igdb/image/upload/t_thumb/pgnpm55mntgebyiov0re.jpg","width":400,"checksum":"74d6bbe1-2057-6835-1e0f-23bff5d28dd9"},{"id":165703,"game":1658,"height":240,"image_id":"ipjnrtg9fyljxnkfg6bk","url":"//images.igdb.com/igdb/image/upload/t_thumb/ipjnrtg9fyljxnkfg6bk.jpg","width":400,"checksum":"97d81608-2753-17c7-f58d-20553ce2bb3f"}],"slug":"mighty-final-fight","summary":"The Mad Gear Gang has spread crime and violence throughout the streets of Metro City. Only one man has enough guts to take the streets back from them, Mayor Mike Haggar. Now the Mad Gear Gang has kidnapped his daughter Jessica to bring him under their control. But they've made one mistake: Haggar's furious and he wants someone's head! Guy and Jessica's boyfriend, Cody, are joining Haggar to clean up the slime-filled streets and rescue Jessica. Along the way you'll find food to replenish your health, or better yet, search for weapons to knock the living daylights out of your enemies. So join Haggar and his friends as they try to free the city from the evil clutches of the Mad Gear Gang!","total_rating":75.5323374315352,"total_rating_count":17,"url":"https://www.igdb.com/games/mighty-final-fight"}