{"id":18613,"cover":{"id":175627,"alpha_channel":false,"animated":false,"game":18613,"height":1889,"image_id":"co3rij","url":"//images.igdb.com/igdb/image/upload/t_thumb/co3rij.jpg","width":1417,"checksum":"98e8532b-f8da-f631-46f0-603a0de407c2"},"first_release_date":740966400,"genres":[{"id":10,"name":"Racing"}],"involved_companies":[{"id":34339,"company":{"id":818,"name":"Atlus"},"created_at":1459641600,"developer":false,"game":18613,"porting":false,"publisher":true,"supporting":false,"updated_at":1459728000,"checksum":"f0138b36-a42d-6a89-698c-1e4d81981efa"},{"id":34340,"company":{"id":2802,"name":"Denki"},"created_at":1459641600,"developer":true,"game":18613,"porting":false,"publisher":false,"supporting":false,"updated_at":1459728000,"checksum":"b62316ee-06e2-9aa9-566e-5070d971a875"}],"name":"GP-1","screenshots":[{"id":22362,"game":18613,"height":672,"image_id":"muw25t7y2rlfac3sbh7h","url":"//images.igdb.com/igdb/image/upload/t_thumb/muw25t7y2rlfac3sbh7h.jpg","width":768,"checksum":"8f44842e-1762-272a-b498-46eb4bad4a91"},{"id":22363,"game":18613,"height":480,"image_id":"n0vealavv8txksjyxcxw","url":"//images.igdb.com/igdb/image/upload/t_thumb/n0vealavv8txksjyxcxw.jpg","width":640,"checksum":"f1665e40-a5e5-a8b8-4c76-f847130af531"}],"slug":"gp-1","storyline":"GP-1 is a motorcycle racing game developed by Genki and published by Atlus for the SNES, which was released in 1993.","summary":"GP-1 is a motorcycle racing game developed by Genki and published by Atlus for the SNES, which was released in 1993.","url":"https://www.igdb.com/games/gp-1","videos":[{"id":7691,"game":18613,"name":"Gameplay video","video_id":"bQ9L4RTa8d4","checksum":"06e9ebb1-6a21-eeaf-c791-40dfab588d38"},{"id":40885,"game":18613,"name":"Game Intro","video_id":"OHkR9lnuC4Q","checksum":"c40f0c82-e8e8-5d48-2707-f41f20b776c5"}]}