{"id":61349,"collection":{"id":3376,"created_at":1507559754,"games":[6302,7787,17458,43881,44434,49085,49994,61344,61345,61347,61349,65308,81527],"name":"Black Bass","slug":"black-bass","updated_at":1656012130,"url":"https://www.igdb.com/collections/black-bass","checksum":"259cd3fe-ad52-a358-c365-1bcf7b6586bb"},"cover":{"id":41351,"game":61349,"height":384,"image_id":"vo1lihb3qsvpe7wbh6cy","url":"//images.igdb.com/igdb/image/upload/t_thumb/vo1lihb3qsvpe7wbh6cy.jpg","width":330,"checksum":"c121b507-ce4f-9c3f-18ee-c21a58ff2c9d"},"first_release_date":814147200,"name":"Hyper Black Bass '95","slug":"hyper-black-bass-95","summary":"Hyper Black Bass '95 is a fishing game for Game Boy, in the famous \"Black Bass\" series.","url":"https://www.igdb.com/games/hyper-black-bass-95"}