{"id":62598,"alternative_names":[{"id":91030,"name":"ぬ～ぼ～"},{"id":91124,"name":"ぬーぼー"}],"cover":{"id":232746,"alpha_channel":false,"animated":false,"game":62598,"height":1009,"image_id":"co4zl6","url":"//images.igdb.com/igdb/image/upload/t_thumb/co4zl6.jpg","width":757,"checksum":"4bbdb3d6-577d-27dc-4ccd-b1fba5d5bfb2"},"first_release_date":724032000,"genres":[{"id":8,"name":"Platform"},{"id":9,"name":"Puzzle"}],"involved_companies":[{"id":127805,"company":{"id":1287,"name":"Irem"},"created_at":1620202624,"developer":true,"game":62598,"porting":false,"publisher":true,"supporting":false,"updated_at":1620208048,"checksum":"376217bb-a69a-b7fa-7eea-54399017a9a8"}],"name":"Noobow","screenshots":[{"id":808498,"alpha_channel":true,"animated":false,"game":62598,"height":144,"image_id":"schbua","url":"//images.igdb.com/igdb/image/upload/t_thumb/schbua.jpg","width":160,"checksum":"e36640f3-d1ab-7749-b14e-a78985fb0b7a"},{"id":808499,"alpha_channel":true,"animated":false,"game":62598,"height":144,"image_id":"schbub","url":"//images.igdb.com/igdb/image/upload/t_thumb/schbub.jpg","width":160,"checksum":"07fae7de-8a2a-2923-718b-62f94439f1b6"},{"id":808500,"alpha_channel":true,"animated":false,"game":62598,"height":144,"image_id":"schbuc","url":"//images.igdb.com/igdb/image/upload/t_thumb/schbuc.jpg","width":160,"checksum":"a2c804b4-21b7-2bd3-5e20-874b120c438d"},{"id":808501,"alpha_channel":true,"animated":false,"game":62598,"height":144,"image_id":"schbud","url":"//images.igdb.com/igdb/image/upload/t_thumb/schbud.jpg","width":160,"checksum":"d56a25df-7072-cdee-f3d8-8be4ba9de9bc"},{"id":808502,"alpha_channel":true,"animated":false,"game":62598,"height":144,"image_id":"schbue","url":"//images.igdb.com/igdb/image/upload/t_thumb/schbue.jpg","width":160,"checksum":"6254bdd5-d19e-d317-9dee-b907917f2844"},{"id":808503,"alpha_channel":true,"animated":false,"game":62598,"height":144,"image_id":"schbuf","url":"//images.igdb.com/igdb/image/upload/t_thumb/schbuf.jpg","width":160,"checksum":"d04d46d8-e9e0-df2d-b2b7-191c6f3ac478"},{"id":808504,"alpha_channel":true,"animated":false,"game":62598,"height":144,"image_id":"schbug","url":"//images.igdb.com/igdb/image/upload/t_thumb/schbug.jpg","width":160,"checksum":"b73650ce-a125-62b0-31fa-e3d63ba5c9ff"}],"slug":"noobow","summary":"Noobow is a puzzle platformer featuring a Japanese chocolate mascot. The aim of the game is to pick up objects and use them wherever they're needed in order to stop the sun and rain from fighting each other. After using the objects in the right places they disappear to confirm that players have made the right choice.\n\nThere are 7 levels in the game and Noobow will always refuse to put his life in danger. Completing each level is done by reaching the goal and assisting the characters that are waiting there.","url":"https://www.igdb.com/games/noobow"}