{"id":49990,"collection":{"id":4939,"created_at":1512905057,"games":[49990,71222],"name":"Towers","slug":"towers","updated_at":1512905057,"url":"https://www.igdb.com/collections/towers","checksum":"314eec22-2506-8bda-e4b8-b83a32453471"},"cover":{"id":232438,"alpha_channel":false,"animated":false,"game":49990,"height":499,"image_id":"co4zcm","url":"//images.igdb.com/igdb/image/upload/t_thumb/co4zcm.jpg","width":375,"checksum":"496fd351-8c6c-3bec-13d5-831b96073fc4"},"first_release_date":964051200,"genres":[{"id":12,"name":"Role-playing (RPG)"}],"name":"Towers: Lord Baniff's Deceit","slug":"towers-lord-baniffs-deceit","summary":"As the war rages on between Airatose and Sagon, a band of adventurers departs to join the war. However, their ship is damaged in a storm, and they stop on an undiscovered island known as Lamini. Lord Banniff gives the adventurers shelter and materials to repair their ship. On the eve of their departure, the adventurers discover something sinister about Lord Banniff. You must take control of one of the adventurers, each with relative strengths and weaknesses, and try to escape from Lord Banniff's castle. Explore 15 levels, battle hundreds of monsters, and find useful items and weapons. If exploring the castle by yourself becomes tedious, use a link cable and have a friend join the adventure. Try to escape from Lord Banniff in TOWERS: Lord Banniff's Deceit","url":"https://www.igdb.com/games/towers-lord-baniffs-deceit"}