{"id":18581,"cover":{"id":14890,"game":18581,"height":1352,"image_id":"jbhr1kwiu560vhyyuoxq","url":"//images.igdb.com/igdb/image/upload/t_thumb/jbhr1kwiu560vhyyuoxq.jpg","width":1000,"checksum":"bb002828-4c61-b268-35ad-6bb0293f41dc"},"first_release_date":410140800,"genres":[{"id":5,"name":"Shooter"},{"id":33,"name":"Arcade"}],"involved_companies":[{"id":34290,"company":{"id":5907,"name":"Telesys"},"created_at":1459468800,"developer":true,"game":18581,"porting":false,"publisher":true,"supporting":false,"updated_at":1459468800,"checksum":"11541a2f-c345-058f-c6da-8865fa134e28"}],"name":"Ram It","slug":"ram-it","summary":"From the left and right sides of the screen colored columns stretch towards the center of the screen in order to connect with their counterpart on the opposite side. The player is at the center of the screen where he can move up and down and has to shoot left and right at the extending columns before they connect.","url":"https://www.igdb.com/games/ram-it"}